_cnest.cpython-38-x86_64-linux-gnu.so
cnest/format.py
cnest/__init__.py
cnest/nest.cpp
cnest-1.1.1.dist-info/WHEEL
cnest-1.1.1.dist-info/RECORD
cnest-1.1.1.dist-info/top_level.txt
cnest-1.1.1.dist-info/LICENSE
cnest-1.1.1.dist-info/METADATA
